atompack/__init__.py
atompack/atom.py
atompack/bond.py
atompack/constants.py
atompack/molecule.py
atompack/symmetry.py
atompack/topology.py
atompack/crystal/__init__.py
atompack/crystal/components.py
atompack/crystal/crystal.py
atompack/crystal/spatial.py
atompack/crystal/transform.py
atompack/data/spacegroups.json
atompack-0.4.3.dist-info/LICENSE
atompack-0.4.3.dist-info/METADATA
atompack-0.4.3.dist-info/WHEEL
atompack-0.4.3.dist-info/top_level.txt
atompack-0.4.3.dist-info/RECORD
