Metadata-Version: 2.1
Name: atompack
Version: 0.4.3
Summary: A flexible Python library for atomic structure generation.
Home-page: https://github.com/seatonullberg/atompack
Author: Seaton Ullberg
Author-email: seatonullberg@gmail.com
License: MIT License
Platform: UNKNOWN
Provides-Extra: dev
Requires-Dist: isort ; extra == 'dev'
Requires-Dist: mypy ; extra == 'dev'
Requires-Dist: pdoc3 ; extra == 'dev'
Requires-Dist: pyflakes ; extra == 'dev'
Requires-Dist: pytest ; extra == 'dev'
Requires-Dist: pytest-benchmark ; extra == 'dev'
Requires-Dist: yapf ; extra == 'dev'
